gmsh_utils/__init__.py
gmsh_utils/__version__.py
gmsh_utils/globals.py
gmsh_utils/gmsh_IO.py
gmsh_utils/math_utils.py
gmsh_utils-1.1.1.dist-info/LICENSE.md
gmsh_utils-1.1.1.dist-info/METADATA
gmsh_utils-1.1.1.dist-info/WHEEL
gmsh_utils-1.1.1.dist-info/top_level.txt
gmsh_utils-1.1.1.dist-info/RECORD
