Metadata-Version: 2.2
Name: gmsh_utils
Version: 1.1.1
Summary: Utilities for gmsh
Author: attr: gmsh_utils.__author__
Classifier: Programming Language :: Python :: 3
Classifier: License :: OSI Approved :: BSD License
Classifier: Operating System :: Microsoft :: Windows
Classifier: Operating System :: Unix
Requires-Python: >=3.8
License-File: LICENSE.md
Requires-Dist: gmsh==4.11
Requires-Dist: numpy>=1.24
Provides-Extra: testing
Requires-Dist: pytest>=7.2; extra == "testing"
Requires-Dist: pytest-cov>=4.0; extra == "testing"
Requires-Dist: tox>=4.4; extra == "testing"
Requires-Dist: mypy>=1.1; extra == "testing"
